netsuite_client/__init__.py
netsuite_client/client.py
netsuite_client/tests/test_client.py
netsuite_client-0.1.1.dist-info/licenses/LICENSE
netsuite_client-0.1.1.dist-info/METADATA
netsuite_client-0.1.1.dist-info/WHEEL
netsuite_client-0.1.1.dist-info/top_level.txt
netsuite_client-0.1.1.dist-info/RECORD
