Metadata-Version: 2.4
Name: netsuite-client
Version: 0.1.1
Summary: A Python client library for interacting with NetSuite's REST and SuiteQL APIs
Author-email: "Continuous AI, Inc." <info@continuous.ai>
License-Expression: BSD-3-Clause
Project-URL: Homepage, https://github.com/Continuous-AI/netsuite-client
Classifier: Development Status :: 4 - Beta
Classifier: Intended Audience :: Developers
Classifier: Operating System :: OS Independent
Classifier: Programming Language :: Python :: 3
Classifier: Programming Language :: Python :: 3.7
Classifier: Programming Language :: Python :: 3.8
Classifier: Programming Language :: Python :: 3.9
Classifier: Programming Language :: Python :: 3.10
Classifier: Programming Language :: Python :: 3.11
Requires-Python: >=3.7
License-File: LICENSE
Requires-Dist: oauthlib>=3.2.2
Requires-Dist: requests-oauthlib>=1.3.1
Requires-Dist: requests>=2.31.0
Dynamic: license-file
